<?xml version="1.0"?>
<psalm
    errorLevel="1"
    resolveFromConfigFile="true"
    xmlns:xsi="http://www.w3.org/2001/XMLSchema-instance"
    xmlns="https://getpsalm.org/schema/config"
    xsi:schemaLocation="https://getpsalm.org/schema/config vendor/vimeo/psalm/config.xsd"
    errorBaseline="psalm-baseline3.xml"
    autoloader="vendor/autoload.php"
>
    <projectFiles>
        <directory name="protected" />
        <directory name="tests/_support" />
        <ignoreFiles>
            <directory name="vendor"/>
        </ignoreFiles>
    </projectFiles>
    <stubs>
        <file name="protected/entry.php" />
        <file name="vendor/yiisoft/yii2/BaseYii.php" />
    </stubs>
</psalm>
